asyncloop/__init__.py
asyncloop/job.py
asyncloop/set.py
asyncloop/thread.py
asyncloop-0.0.1.dev2.dist-info/DESCRIPTION.rst
asyncloop-0.0.1.dev2.dist-info/METADATA
asyncloop-0.0.1.dev2.dist-info/RECORD
asyncloop-0.0.1.dev2.dist-info/WHEEL
asyncloop-0.0.1.dev2.dist-info/metadata.json
asyncloop-0.0.1.dev2.dist-info/top_level.txt
