Metadata-Version: 2.0
Name: asyncloop
Version: 0.0.1.dev2
Summary: A Celery-like event loop with asyncio and no more dependencies
Home-page: https://github.com/dgkim5360/asyncloop
Author: Don Kim
Author-email: dgkimdev@gmail.com
License: MIT
Keywords: asyncio celery event loop
Platform: UNKNOWN
Classifier: Development Status :: 3 - Alpha
Classifier: License :: OSI Approved :: MIT License
Classifier: Framework :: AsyncIO
Classifier: Programming Language :: Python :: 3 :: Only
Classifier: Programming Language :: Python :: 3.5
Requires-Python: >=3.5
